codelib/__init__.py
codelib/base.py
codelib/rot.py
codelib-0.0.1.dist-info/LICENSE
codelib-0.0.1.dist-info/METADATA
codelib-0.0.1.dist-info/WHEEL
codelib-0.0.1.dist-info/top_level.txt
codelib-0.0.1.dist-info/RECORD
