Metadata-Version: 2.1
Name: codelib
Version: 0.0.1
Summary: handy tool encoding and decoding
Home-page: https://github.com/Madhava-mng/codelib
Author: Madhava
Author-email: alformint@gmail.com
License: UNKNOWN
Platform: UNKNOWN
Classifier: Programming Language :: Python :: 3
Classifier: License :: OSI Approved :: MIT License
Classifier: Operating System :: OS Independent
Requires-Python: >=3.6
